few_colors/as_application.py
few_colors/as_command.py
few_colors/few_colors.py
few_colors/input.py
few_colors-2021.2.dist-info/METADATA
few_colors-2021.2.dist-info/WHEEL
few_colors-2021.2.dist-info/entry_points.txt
few_colors-2021.2.dist-info/top_level.txt
few_colors-2021.2.dist-info/RECORD
