Metadata-Version: 2.1
Name: few-colors
Version: 2021.2
Summary: Color Image with Few Colors from an image with Labeled Objects
Home-page: https://gitlab.inria.fr/edebreuv/fewcolors
Author: Eric Debreuve
Author-email: eric.debreuve@univ-cotedazur.fr
License: UNKNOWN
Project-URL: Source, https://gitlab.inria.fr/edebreuv/fewcolors
Keywords: image,labeled objects,colors
Platform: UNKNOWN
Classifier: Topic :: Scientific/Engineering :: Image Recognition
Classifier: Intended Audience :: Science/Research
Classifier: License :: OSI Approved :: CEA CNRS Inria Logiciel Libre License, version 2.1 (CeCILL-2.1)
Classifier: Programming Language :: Python :: 3.8
Classifier: Development Status :: 5 - Production/Stable
Requires-Python: >=3.8
Requires-Dist: imageio
Requires-Dist: matplotlib
Requires-Dist: networkx
Requires-Dist: numpy
Requires-Dist: PySide2
Requires-Dist: scikit-image
Requires-Dist: scipy
